gene_similarity/__init__.py
gene_similarity/__main__.py
gene_similarity/calculate_similarity.py
gene_similarity/cli.py
gene_similarity/output.py
gene_similarity/parser.py
gene_similarity-0.1.0.dist-info/LICENSE
gene_similarity-0.1.0.dist-info/METADATA
gene_similarity-0.1.0.dist-info/WHEEL
gene_similarity-0.1.0.dist-info/entry_points.txt
gene_similarity-0.1.0.dist-info/top_level.txt
gene_similarity-0.1.0.dist-info/RECORD
