Metadata-Version: 2.1
Name: gene-similarity
Version: 0.1.0
Summary: A package for visualizing gene similarity
Home-page: https://github.com/farhangus/Gene_similarity
Author: Farhang
Author-email: youremail@example.com
License: MIT
Classifier: Programming Language :: Python :: 3
Classifier: License :: OSI Approved :: MIT License
Classifier: Operating System :: OS Independent
Requires-Python: >=3.6
License-File: LICENSE
Requires-Dist: seaborn
Requires-Dist: matplotlib
Requires-Dist: pandas
Requires-Dist: click
Requires-Dist: numpy
Requires-Dist: scipy
Requires-Dist: networkx
